README.md
setup.py
dataapi_e8/__init__.py
dataapi_e8/baseapi.py
dataapi_e8/utils/__init__.py
dataapi_e8/utils/helper.py
dataapi_e8/utils/powerUtils.py
dataapi_e8/utils/meters/__init__.py
dataapi_e8/utils/meters/electric.py
dataapi_e8/utils/meters/th.py
dataapi_e8/utils/meters/water.py
jx_dataapi_e8.egg-info/PKG-INFO
jx_dataapi_e8.egg-info/SOURCES.txt
jx_dataapi_e8.egg-info/dependency_links.txt
jx_dataapi_e8.egg-info/requires.txt
jx_dataapi_e8.egg-info/top_level.txt