Metadata-Version: 2.1
Name: jx-dataapi-e8
Version: 0.0.8
Summary: xjiaxun gateway data api v.E8
Home-page: http://www.xjiaxun.com
Author: tusky
Author-email: zj2012yhd@163.com
Maintainer: tusky
Maintainer-email: zj2012yhd@163.com
License: MIT
Platform: all
Classifier: Operating System :: OS Independent
Classifier: License :: OSI Approved :: MIT License
Classifier: Programming Language :: Python :: 3.6
Classifier: Programming Language :: Python :: 3.7
